{
  "project_info": {
    "project_number": "296377663659",
    "project_id": "nutria-f8872",
    "storage_bucket": "nutria-f8872.appspot.com"
  },
  "client": [
    {
      "client_info": {
        "mobilesdk_app_id": "1:296377663659:android:1b6b8754aebcf2af61b7ee",
        "android_client_info": {
          "package_name": "com.nutria.nutria"
        }
      },
      "oauth_client": [
        {
          "client_id": "296377663659-kkiltud51diiemba7ik092h09l2bjgcp.apps.googleusercontent.com",
          "client_type": 3
        }
      ],
      "api_key": [
        {
          "current_key": "AIzaSyCZroAov_kIPlJpjFe87oMzB5JxK_uS3VM"
        }
      ],
      "services": {
        "appinvite_service": {
          "other_platform_oauth_client": [
            {
              "client_id": "296377663659-kkiltud51diiemba7ik092h09l2bjgcp.apps.googleusercontent.com",
              "client_type": 3
            },
            {
              "client_id": "296377663659-029kls8bk5hcnjdk2tqn5ssjici3r5nk.apps.googleusercontent.com",
              "client_type": 2,
              "ios_info": {
                "bundle_id": "com.alamsyah.nutria"
              }
            }
          ]
        }
      }
    }
  ],
  "configuration_version": "1"
}